colorgram/__init__.py
colorgram/colorgram.py
colorgram.py-1.0.0.dist-info/DESCRIPTION.rst
colorgram.py-1.0.0.dist-info/METADATA
colorgram.py-1.0.0.dist-info/RECORD
colorgram.py-1.0.0.dist-info/WHEEL
colorgram.py-1.0.0.dist-info/metadata.json
colorgram.py-1.0.0.dist-info/top_level.txt
