Metadata-Version: 2.0
Name: colorgram.py
Version: 1.0.0
Summary: A Python module for extracting colors from images. Get a palette of any picture!
Home-page: https://github.com/obskyr/colorgram.py
Author: Samuel Messner
Author-email: powpowd@gmail.com
License: MIT
Download-URL: https://github.com/obskyr/colorgram.py/tarball/v1.0.0
Keywords: color colors palette extract image picture
Platform: UNKNOWN
Classifier: Development Status :: 5 - Production/Stable
Classifier: Intended Audience :: Developers
Classifier: Programming Language :: Python
Classifier: Natural Language :: English
Classifier: License :: OSI Approved :: MIT License
Classifier: Programming Language :: Python :: 2.7
Classifier: Programming Language :: Python :: 3
Classifier: Programming Language :: Python :: 3.2
Classifier: Programming Language :: Python :: 3.3
Classifier: Programming Language :: Python :: 3.4
Classifier: Programming Language :: Python :: 3.5
Classifier: Topic :: Software Development :: Libraries :: Python Modules
Classifier: Topic :: Utilities
Requires-Dist: pillow (>=3.3.1)
